cactive/__init__.py
cactive/hypixel_nick_tracker/__init__.py
cactive/hypixel_nick_tracker/classes.py
cactive/ip/__init__.py
cactive-1.0.0.dist-info/LICENSE.md
cactive-1.0.0.dist-info/METADATA
cactive-1.0.0.dist-info/WHEEL
cactive-1.0.0.dist-info/top_level.txt
cactive-1.0.0.dist-info/RECORD
