Metadata-Version: 2.1
Name: cactive
Version: 1.0.0
Summary: All of the Cactive NPM modules rewritten in Python
Home-page: https://github.com/CactiveNetwork/cactive-rewrites/tree/main/python/
Author: Cactive
Author-email: legal@cactive.network
Project-URL: Bug Tracker, https://github.com/CactiveNetwork/cactive-rewrites/tree/main/python/issues
Classifier: Programming Language :: Python :: 3
Classifier: License :: Other/Proprietary License
Classifier: Operating System :: OS Independent
Requires-Python: >=3.9
License-File: LICENSE.md
Requires-Dist: requests (==2.28.1)
